{
  "cells": {
    "20": {
      "stdout": "14:27:00 - INFO - LOGGING (log: True)\n14:27:00 - INFO - BLOCKS (total: 17, dynamic: 3, static: 14, eventful: 2)\n14:27:00 - INFO - GRAPH (nodes: 17, edges: 22, alg. depth: 6, loop depth: 0, runtime: 0.054ms)\n14:27:00 - INFO - STARTING -> TRANSIENT (Duration: 30.00s)\n14:27:00 - INFO - --------------------   1% | 0.0s<2.1s | 2896.8 it/s\n14:27:01 - INFO - ####----------------  20% | 0.4s<1.5s | 2910.6 it/s\n14:27:01 - INFO - ########------------  40% | 0.8s<1.3s | 2879.8 it/s\n14:27:01 - INFO - ############--------  60% | 1.2s<0.7s | 3042.3 it/s\n14:27:02 - INFO - ################----  80% | 1.6s<0.5s | 2056.9 it/s\n14:27:02 - INFO - #################### 100% | 2.3s<--:-- | 2149.2 it/s\n14:27:02 - INFO - FINISHED -> TRANSIENT (total steps: 5837, successful: 4942, runtime: 2261.94 ms)\n",
      "stderr": null,
      "figures": []
    },
    "22": {
      "stdout": null,
      "stderr": null,
      "figures": [
        "dcmotor_control_0.png",
        "dcmotor_control_1.png"
      ]
    }
  },
  "executedAt": "2026-01-22T13:27:03.897557+00:00",
  "duration": 5598,
  "success": true
}